{
    "Locations":[
    {"Team":"AFC Rushden & Diamonds","Latitude":"52.2933239","Longitude":"-0.6835504"},
    {"Team":"Alvechurch","Latitude":"52.3448529","Longitude":"-1.9565"},
    {"Team":"Banbury United","Latitude":"52.0567041","Longitude":"-1.3265"},
    {"Team":"Barwell","Latitude":"52.5726244","Longitude":"-1.344006"},
    {"Team":"Bedworth Town","Latitude":"52.4764692","Longitude":"-1.472"},
    {"Team":"Biggleswade Town","Latitude":"52.0767383","Longitude":"-0.269"},
    {"Team":"Coalville Town","Latitude":"52.7231672","Longitude":"-1.3818057"},
    {"Team":"Halesowen Town","Latitude":"52.4538486","Longitude":"-2.0576845"},
    {"Team":"Hitchin Town","Latitude":"51.9539872","Longitude":"-0.284"},
    {"Team":"Kettering Town","Latitude":"52.3667201","Longitude":"-0.6903104"},
    {"Team":"King's Lynn Town","Latitude":"52.7501624","Longitude":"0.407"},
    {"Team":"Leiston","Latitude":"52.2046195","Longitude":"1.5714794"},
    {"Team":"Lowestoft Town","Latitude":"52.4802054","Longitude":"1.7476257"},
    {"Team":"Needham Market","Latitude":"52.1506972","Longitude":"1.0455622"},
    {"Team":"Redditch United","Latitude":"52.3076929","Longitude":"-1.9521753"},
    {"Team":"Royston Town","Latitude":"52.0523232","Longitude":"-0.0171837"},
    {"Team":"Rushall Olympic","Latitude":"52.6009101","Longitude":"-1.9526149"},
    {"Team":"St Ives Town","Latitude":"52.3304804","Longitude":"-0.0823639"},
    {"Team":"St Neots Town","Latitude":"52.2328713","Longitude":"-0.2453034"},
    {"Team":"Stourbridge","Latitude":"52.4626028","Longitude":"-2.1506229"},
    {"Team":"Stratford Town","Latitude":"52.1946241","Longitude":"-1.676422"},
    {"Team":"Tamworth","Latitude":"52.6290152","Longitude":"-1.6892374"},
    ]
} 
